simulo/__init__.py
simulo/config.py
simulo/simulomath.py
simulo/auth/__init__.py
simulo/auth/authenticator.py
simulo/cli/__init__.py
simulo/cli/runner.py
simulo/upload/__init__.py
simulo/upload/data_upload.py
simulo/utils/__init__.py
simulo/utils/json_transformations.py
simulo/utils/unique_id.py
simulo-0.2.6.dist-info/LICENSE
simulo-0.2.6.dist-info/METADATA
simulo-0.2.6.dist-info/WHEEL
simulo-0.2.6.dist-info/entry_points.txt
simulo-0.2.6.dist-info/top_level.txt
simulo-0.2.6.dist-info/RECORD
