Metadata-Version: 2.1
Name: simulo
Version: 0.2.6
Summary: The Simulo SDK
Home-page: UNKNOWN
Author: The Simulo Team
License: No License specified
Platform: UNKNOWN
Classifier: Intended Audience :: Developers
Classifier: License :: OSI Approved :: MIT License
Classifier: Programming Language :: Python
Classifier: Programming Language :: Python :: 3
Classifier: Programming Language :: Python :: 3.6
Classifier: Programming Language :: Python :: 3.7
Classifier: Programming Language :: Python :: 3.8
Classifier: Programming Language :: Python :: 3.9
Classifier: Operating System :: OS Independent
License-File: LICENSE
Requires-Dist: numpy
Requires-Dist: requests
Requires-Dist: requests-toolbelt
Requires-Dist: PyJWT
Requires-Dist: click
